{
  "DCA": {
    "Diseño académico": [
      "Académica",
      "Académico",
      "Aprendizaje",
      "Blandas",
      "Capacidad",
      "Capítulo",
      "Certificación",
      "Conocimiento",
      "Contenido",
      "Currículo",
      "Desarrollo",
      "Directiva",
      "Duras",
      "EFI",
      "Escuela",
      "Estrategia",
      "Evaluación",
      "Experiencia",
      "Extensión",
      "FIC",
      "Feria",
      "Formación",
      "Gestión",
      "Habilidad",
      "Innovación",
      "Institucional",
      "Integración",
      "Metodología",
      "Olimpiada",
      "Planificación",
      "Reforma",
      "SIEA",
      "SIGEDA",
      "SÉ",
      "Skills",
      "Soporte",
      "Staff",
      "Subdirectora",
      "Subdirector",
      "Taller",
      "Tutoría"
    ],
    "Innovación e investigación": [
      "Académica",
      "Académico",
      "COEXPRO",
      "Consultoría",
      "Ciclo",
      "Diseño",
      "Entorno",
      "Estadística",
      "Experimentación",
      "Extensión",
      "Conocimiento",
      "Herramienta",
      "I+D+I",
      "Innovación",
      "Investigación",
      "Mentoría",
      "Soporte",
      "Staff"
    ],
    "Formación y capacitación": [
      "Actividad",
      "Acreditación",
      "Capacitación",
      "Charla",
      "Conferencia",
      "Consultoría",
      "Curso",
      "Desarrollo",
      "Director",
      "Entrenamiento",
      "Escuela",
      "Estrategia",
      "FIC",
      "EFI",
      "Formación",
      "Ingeolimpiada",
      "Liderazgo",
      "Mentoría",
      "Olimpiada",
      "Profesional",
      "Seminario",
      "Simposio",
      "Taller"
    ]
  },
  "DCC": {
    "Estrategia de comunicación": [
      "Alcance",
      "Campaña",
      "Comunicación",
      "Difusión",
      "Digital",
      "Estrategia",
      "Feedback",
      "Marca",
      "Comunicativa",
      "Impacto",
      "Imagen",
      "Interacción",
      "Manual",
      "Medios",
      "MIC",
      "Plan",
      "Posicionamiento",
      "Podcast",
      "Publicidad",
      "Red",
      "Relación",
      "Segmentación",
      "Sistema",
      "Youtube"
    ],
    "Producción audiovisual": [
      "Animación",
      "Animaciones",
      "Audiovisual",
      "Visual",
      "Calidad",
      "Contenido",
      "Concepto",
      "Comunicaciones",
      "Comunicación",
      "Creativa",
      "Diseño",
      "Edición",
      "Grabación",
      "Guiones",
      "Infografía",
      "Streaming",
      "Podcast",
      "Producción",
      "Publicidad",
      "Red",
      "Tiktok",
      "Video",
      "Youtube"
    ],
    "Gestión de documental": [
      "Almacenamiento",
      "Documental",
      "Archivo",
      "Digital",
      "Base de datos",
      "Biblioteca",
      "Clasificación",
      "Información",
      "Documental",
      "Documentación",
      "Gestión",
      "Metadato",
      "Indexación",
      "Integridad",
      "Metadatos",
      "Manual",
      "Normatividad",
      "Política",
      "Preservación",
      "SIGEDA",
      "Sistema",
      "Recuperación"
    ]
  },
  "DCD": {
    "Gestión de asociados": [
      "Acompañamiento",
      "Adaptación",
      "Perfil",
      "Bienestar",
      "Carnetización",
      "Capítulo",
      "Cultura",
      "Desarrollo",
      "Directiva",
      "Encuesta",
      "Expansión",
      "Fidelización",
      "Feedback",
      "Gala",
      "Gestión",
      "Inclusión",
      "Incentivo",
      "Legado",
      "Networking",
      "Persuasión",
      "Padrino",
      "Padrinazgo",
      "Afiliación",
      "Membresía",
      "Reclutamiento",
      "Representación",
      "Retención",
      "SÉ",
      "SRA",
      "Subdirector",
      "Subdirectora",
      "FRAN",
      "SRA",
      "ANEIAP DAY",
      "Gira"
    ],
    "Integración y bienestar": [
      "Acompañamiento",
      "Bienestar",
      "Clima",
      "Organizacional",
      "Conformación",
      "Convivencia",
      "Cultura",
      "Desarrollo",
      "Diversidad",
      "Encuentro",
      "FRAC",
      "FRAN",
      "FRAR",
      "FRAS",
      "Gala",
      "Gira",
      "Incentivo",
      "Integración",
      "Legado",
      "Liderazgo",
      "Madrina",
      "Padrinazgo",
      "Padrino",
      "Personal",
      "Plan",
      "Premios",
      "Relación",
      "Recurso",
      "Humano",
      "RRHH",
      "Salud mental",
      "Voluntariado",
      "Workshop",
      "SÉ",
      "SRA"
    ],
     "Sostenimiento y sociedad": [
      "Ambiente",
      "Ambiental",
      "Cooperación",
      "Comunitario",
      "Social",
      "Desarrollo",
      "Eco",
      "Ética",
      "Impacto",
      "Inclusión",
      "Iniciativa",
      "Parque",
      "Playa",
      "Comunitario",
      "Proyecto",
      "Intercultural",
      "Responsabilidad",
      "RSA",
      "Social",
      "Sostenibilidad",
      "Sustentabilidad"
      ]
  },
  "DCF": {
    "Gestión financiera": [
      "Ahorro",
      "Auditoría",
      "Balance",
      "Capitalización",
      "Contabilidad",
      "Consolidación",
      "Control",
      "Dashboard",
      "Egreso",
      "Financiero",
      "Finanzas",
      "Flujo",
      "Fondo",
      "Fuente",
      "Gestión",
      "Ingreso",
      "Liquidez",
      "Presupuestaria",
      "Indicadores",
      "Ingreso",
      "Monitoreo",
      "Plan",
      "Política",
      "Proyección",
      "Proyecciones",
      "Recurso",
      "Rendición",
      "Reporte",
      "Revisión",
      "Riesgo",
      "Solidez",
      "Sustentable"
    ],
    "Sostenibilidad económica": [
      "Alternativa",
      "Capital",
      "Costo",
      "Desarrollo",
      "Diversificación",
      "Económica",
      "Estrategia",
      "Financiación",
      "Financiamiento",
      "Fuente",
      "Gestión",
      "Modelo",
      "Obtención",
      "Optimización",
      "Planeación",
      "Proyecto",
      "Recaudación",
      "Recurso",
      "Rentabilidad",
      "Retorno",
      "Riqueza",
      "Sostenibilidad",
      "Sostenimiento",
      "Viabilidad"
    ],
    "Análisis y transparencia": [
      "Análisis",
      "Auditoría",
      "Certificación",
      "Financiera",
      "Control",
      "Cumplimiento",
      "Directiva",
      "Donaciones",
      "Ética",
      "Indicadores",
      "Informe",
      "Norma",
      "Normativa",
      "Reporte",
      "Subdirectora",
      "Subdirector",
      "Trazabilidad",
      "Transparencia",
      "Validación"
    ]
  },
  "DCM": {
    "Estrategias de branding": [
      "Branding",
      "Campaña",
      "Identidad",
      "CRM",
      "Cultura",
      "Diferenciación",
      "Estrategia",
      "Expansión",
      "Identidad",
      "Imagen",
      "Corporativa",
      "Indicador",
      "Logo",
      "Marketing",
      "Mercadeo",
      "Modelo",
      "Negocio",
      "NPS",
      "Plan",
      "Posicionamiento",
      "Promoción",
      "Publicidad",
      "Rebranding",
      "Reconocimiento",
      "Red",
      "SGA",
      "Segmentación",
      "Slogan",
      "Stakeholders",
      "Tienda",
      "Valor"
    ],
    "Promoción y visibilidad": [
      "ANEIAP",
      "Alcance",
      "Buzón",
      "Campaña",
      "Capítulo",
      "Comunidad",
      "Directiva",
      "Dinámica",
      "Embajador",
      "Engagement",
      "Evento",
      "Expansión",
      "Estrategia",
      "Identidad",
      "Marketing",
      "Mercadeo",
      "Negocio",
      "Networking",
      "Posicionamiento",
      "Publicidad",
      "Red",
      "Relaciones",
      "Saloneo",
      "Stakeholders",
      "Subdirector",
      "Subdirectora",
      "Visualización",
      "Visibilidad"
    ],
    "Gestión comercial": [
      "Alianzas",
      "Análisis",
      "Base",
      "Buzón",
      "Canal",
      "Cliente",
      "Comercial",
      "CRM",
      "Crecimiento",
      "E-commerce",
      "EMPRENDE-IAP",
      "Entorno",
      "Estrategia",
      "Experiencia del cliente",
      "Expansión",
      "Externo",
      "Comercial",
      "Interno",
      "Marketing",
      "Mercadeo",
      "Modelo",
      "Negocio",
      "Negociación",
      "Networking",
      "Plan",
      "Posicionamiento",
      "Producto",
      "Prospecto",
      "Propuesta",
      "Publicidad",
      "Relaciones",
      "Servicio",
      "Stakeholders",
      "Tienda",
      "Venta"
    ]
  },
  "PC": {
    "Liderazgo y estrategia": [
      "Estrategia",
      "Directivo",
      "Liderazgo",
      "Rendimiento",
      "Decisiones",
      "Supervisión",
      "Transformación",
      "Gestión del cambio",
      "Toma de decisiones",
      "Motivación intrínseca",
      "Comunicación efectiva",
      "Delegación estratégica",
      "Desarrollo de equipos",
      "Pensamiento crítico",
      "Liderazgo adaptativo",
      "Visión global",
      "Estratégias de éxito",
      "Plan estratégico",
      "Perspectiva global",
      "Liderazgo transformacional",
      "Cultura organizacional",
      "Resolución de conflictos",
      "Coaching",
      "Delegación",
      "Trabajo en equipo",
      "Innovación estratégica"
    ],
    "Gestión organizacional": [
      "Presidencia",
      "Presidente",
      "Directiva",
      "Capítulo",
      "Junta",
      "ECAP",
      "Gestión",
      "Gestor",
      "Coordinación",
      "Procesos operativos",
      "Diagramas de flujo",
      "Gestión de riesgos",
      "Metodologías ágiles",
      "Revisión estratégica",
      "Control de calidad",
      "Benchmarking",
      "Normativa interna",
      "Protocolos",
      "Organización interna",
      "Procesos administrativos",
      "Recursos logísticos",
      "Eficiencia operativa",
      "Estructura capitular",
      "Manejo de crisis",
      "Normativas internas",
      "Revisión organizacional",
      "Plan operativo",
      "Coordinación interdepartamental"
    ],
    "Relaciones y representación": [
      "Representante",
      "ANEIAP DAY",
      "Legal",
      "Negociaciones",
      "Relaciones públicas",
      "Diplomacia",
      "Visitas institucionales",
      "Acuerdos estratégicos",
      "Representatividad",
      "Relaciones externas",
      "Resolución de conflictos",
      "Gestión de imagen",
      "Agenda oficial",
      "Relaciones institucionales",
      "Protocolo",
      "Negociación",
      "Convenios",
      "Networking estratégico",
      "Alianzas",
      "Representación legal",
      "Gestión de intereses",
      "Desarrollo organizacional"
    ]
  },
  "CCP": {
    "Gestión de proyectos": [
      "Proyecto",
      "Project",
      "Capacitación",
      "Capacitaciones",
      "Auditor",
      "SIEA",
      "Desarrollo",
      "Equipo",
      "Estratégico",
      "Modelo",
      "Reforma",
      "Formato",
      "Investigación",
      "Planificación",
      "Ejecución",
      "Control",
      "Proceso",
      "Asesor",
      "Sponsor",
      "Manager",
      "Gestión",
      "Vida",
      "Subcoordinador",
      "Subcoordinadora",
      "Viabilidad",
      "Implementación",
      "Metodologías PMI",
      "Diagramas Gantt",
      "Cronogramas",
      "Ágil-Scrum",
      "Recursos humanos",
      "Stakeholders",
      "Gestión de alcance",
      "Cierre de proyectos",
      "Estimaciones",
      "Matriz RACI",
      "Metodología ágil",
      "PMO",
      "Calendario de proyectos",
      "Factibilidad",
      "Monitoreo",
      "Plan de acción",
      "Alcance del proyecto",
      "Línea base",
      "Riesgos del proyecto",
      "PIN"
    ],
    "Innovación y creatividad": [
      "Proyecto",
      "Innovación",
      "Innova",
      "Desarrollo",
      "ANEIAP",
      "Bolsa",
      "Valores",
      "Implementación",
      "Disruptivo",
      "COEC",
      "Entrenamiento",
      "Organizador",
      "SIEA",
      "Datos",
      "END",
      "DTI",
      "Transversal",
      "Operatividad",
      "Estratégico",
      "Sponsor",
      "Asesor",
      "Analítica",
      "Modelo",
      "Creación",
      "Creaciones",
      "Reforma",
      "Actualización",
      "CNI",
      "GNP",
      "PM",
      "Cambio",
      "Reforma",
      "ALMA",
      "Estructura",
      "Gobierno",
      "Pensamiento lateral",
      "Proyectos disruptivos",
      "Design thinking",
      "Innovación abierta",
      "Modelos de negocio",
      "Colaboración creativa",
      "Crowdsourcing",
      "Ideación",
      "Experimentación",
      "Validación",
      "Prototipos",
      "Diseño conceptual",
      "Nuevas tecnologías",
      "Creatividad estratégica",
      "Innovación incremental",
      "Procesos disruptivos",
      "Emprendimiento",
      "Sistema",
      "Departamento"
    ],
    "Colaboración estratégica": [
      "Proyecto",
      "CNI",
      "GNP",
      "Directiva",
      "ECP",
      "PEN",
      "COEC",
      "Capítulo",
      "Capacitación",
      "Capacitaciones",
      "Integración",
      "Integraciones",
      "Staff",
      "Reclutamiento",
      "Sponsor",
      "Asesor",
      "Organizador",
      "Comité",
      "Transversal",
      "Equipo",
      "Cultura",
      "Evento",
      "Estratégico",
      "PEN",
      "PIN",
      "Fraternidad",
      "ANEIAP DAY",
      "Organización",
      "Asesoramiento",
      "Indicadores",
      "Colaboración",
      "Sinergias",
      "Alianzas público-privadas",
      "Networking estratégico",
      "Creación de redes",
      "Gestión de talento",
      "Análisis de contexto",
      "Interdisciplinariedad",
      "Colaboración remota",
      "Estrategias colaborativas",
      "Responsabilidad compartida",
      "Estrategias colaborativas",
      "Ecosistemas",
      "Impacto social",
      "Modelos de cooperación",
      "Relaciones multilaterales",
      "Redes de contacto",
      "Benchmarking",
      "Consultoría estratégica"
    ]
  },
  "IC": {
    "Auditoría y control": [
      "Interventoría",
      "Normativa",
      "Auditor",
      "Interventor",
      "Datos",
      "Data",
      "Análisis",
      "Ética",
      "Revisión",
      "Asesoría",
      "Evaluación de riesgos",
      "Planificación de auditoría",
      "Verificación",
      "Procedimientos internos",
      "Informes de control",
      "Matriz de evaluación",
      "Diagnóstico interno",
      "Checklist",
      "Indicadores de desempeño",
      "Seguimiento continuo",
      "Revisión de procesos",
      "Calidad",
      "Supervisión",
      "Cumplimiento",
      "Informes de auditoría",
      "Inspección",
      "Mejora continua",
      "Estándares",
      "Rendición de cuentas",
      "Control interno"
    ],
    "Normativa y transparencia": [
      "Transparencia",
      "Reglamento",
      "Interventor",
      "Análisis financiero",
      "Veeduría",
      "Conducto",
      "Conducta",
      "Regular",
      "Reglas de compliance",
      "Código de conducta",
      "Reportes públicos",
      "Declaraciones",
      "Ética normativa",
      "Controles regulatorios",
      "Monitoreo",
      "Estándares ISO",
      "Marcos legales",
      "Transparencia activa",
      "Políticas",
      "Estándares éticos",
      "Marco regulatorio",
      "Procedimientos",
      "Control normativo",
      "Regulaciones",
      "Transparencia asociativa",
      "Estrategias de control",
      "Formalización",
      "Protocolos"
    ],
    "Seguimiento y evaluación": [
      "ECI",
      "360",
      "Estratégica",
      "Directiva",
      "IC",
      "ENI",
      "Capítulo",
      "Interventor",
      "Rúbrica",
      "Indicadores de desempeño",
      "Seguimiento",
      "KPIs",
      "Cuadros de mando",
      "Feedback",
      "Informe ejecutivo",
      "Panel de control",
      "Medición de resultados",
      "Encuestas",
      "Monitoreo periódico",
      "Ajustes estratégicos",
      "Revisiones iterativas",
      "Reportes periódicos",
      "Indicadores de desempeño",
      "Retroalimentación",
      "Planes de mejora",
      "Supervisión constante",
      "Evaluación cualitativa",
      "Auditorías internas",
      "Progreso",
      "Revisiones",
      "Evaluación trimestral"
    ]
  }
}
